debianrfs/__init__.py
debianrfs/bug.py
debianrfs/cache.py
debianrfs/entry.py
debianrfs/main.py
debianrfs/math.py
debianrfs/uploads.py
debian_rfs_stats-0.3.1.dist-info/LICENSE
debian_rfs_stats-0.3.1.dist-info/METADATA
debian_rfs_stats-0.3.1.dist-info/WHEEL
debian_rfs_stats-0.3.1.dist-info/entry_points.txt
debian_rfs_stats-0.3.1.dist-info/RECORD
