Metadata-Version: 2.1
Name: debian-rfs-stats
Version: 0.3.1
Summary: Statistics regarding RFS wait times on Debian.
License: MIT
Author: Maytham Alsudany
Author-email: maytha8thedev@gmail.com
Requires-Python: >=3.11,<4.0
Classifier: License :: OSI Approved :: MIT License
Classifier: Programming Language :: Python :: 3
Classifier: Programming Language :: Python :: 3.11
Classifier: Programming Language :: Python :: 3.12
Requires-Dist: beautifulsoup4 (>=4.12.2,<5.0.0)
Requires-Dist: click (>=8.1.7,<9.0.0)
Requires-Dist: lxml (>=4.9.3,<5.0.0)
Requires-Dist: platformdirs (>=4.0.0,<5.0.0)
Requires-Dist: python-debianbts (>=4.0.2,<5.0.0)
Requires-Dist: python-gnupg (>=0.5.1,<0.6.0)
Requires-Dist: requests (>=2.31.0,<3.0.0)
